hygro_premium_sp/__init__.py
hygro_premium_sp/humidity_extractor.py
hygro_premium_sp/main.py
hygro_premium_sp/public/asset-manifest.json
hygro_premium_sp/public/favicon.ico
hygro_premium_sp/public/index.html
hygro_premium_sp/public/logo192.png
hygro_premium_sp/public/logo512.png
hygro_premium_sp/public/manifest.json
hygro_premium_sp/public/robots.txt
hygro_premium_sp/public/static/js/2.e4ee6e56.chunk.js
hygro_premium_sp/public/static/js/2.e4ee6e56.chunk.js.LICENSE.txt
hygro_premium_sp/public/static/js/2.e4ee6e56.chunk.js.map
hygro_premium_sp/public/static/js/3.6b6aa847.chunk.js
hygro_premium_sp/public/static/js/3.6b6aa847.chunk.js.map
hygro_premium_sp/public/static/js/main.f7d43182.chunk.js
hygro_premium_sp/public/static/js/main.f7d43182.chunk.js.map
hygro_premium_sp/public/static/js/runtime-main.48ed3fca.js
hygro_premium_sp/public/static/js/runtime-main.48ed3fca.js.map
hygro_premium_sp_server-2.dist-info/LICENSE
hygro_premium_sp_server-2.dist-info/METADATA
hygro_premium_sp_server-2.dist-info/WHEEL
hygro_premium_sp_server-2.dist-info/entry_points.txt
hygro_premium_sp_server-2.dist-info/top_level.txt
hygro_premium_sp_server-2.dist-info/RECORD
