Metadata-Version: 2.1
Name: hygro-premium-sp-server
Version: 2
Summary: Unofficial EasyHome Hygro PremiumSP speed controller via exposed web and REST API
Home-page: https://github.com/jamofer/humidity-extractor
Author: Javier Moragón
Author-email: jamofer@gmail.com
License: UNKNOWN
Platform: UNKNOWN
Classifier: Development Status :: 4 - Beta
Classifier: Intended Audience :: End Users/Desktop
Classifier: License :: OSI Approved :: MIT License
Classifier: Operating System :: POSIX :: Linux
Classifier: Programming Language :: Python :: 3.6
Classifier: Topic :: Home Automation
Classifier: Topic :: Internet
Classifier: Topic :: Internet :: WWW/HTTP
Requires-Python: >=3.6
License-File: LICENSE
Requires-Dist: Flask (~=1.1.4)
Requires-Dist: flask-cors
Requires-Dist: RPi.GPIO
Provides-Extra: testing
Requires-Dist: flake8 ; extra == 'testing'
Requires-Dist: pytest ; extra == 'testing'
Requires-Dist: mock ; extra == 'testing'
Requires-Dist: fake-rpigpio ; extra == 'testing'
